oekaki/__init__.py
oekaki/lazy.py
oekaki/validation.py
tests/__init__.py
tests/test_lazy.py
tests/utils.py
oekaki-0.1.0.dist-info/METADATA
oekaki-0.1.0.dist-info/WHEEL
oekaki-0.1.0.dist-info/top_level.txt
oekaki-0.1.0.dist-info/RECORD
