Metadata-Version: 2.1
Name: oekaki
Version: 0.1.0
Summary: Lazy on demand subplots.
Home-page: https://github.com/yuji96/oekaki
Author: Yuji Yamamoto
License: UNKNOWN
Platform: UNKNOWN
Classifier: Programming Language :: Python :: 3
Requires-Dist: seaborn
Provides-Extra: dev
Requires-Dist: pytest ; extra == 'dev'
Provides-Extra: ja
Requires-Dist: japanize-matplotlib ; extra == 'ja'
